{
  "components": [
    {
      "type": "content",
      "container": "main",
      "components": [
        {
          "type": "row",
          "components": [
            {
              "type": "col",
              "class": "col-md-12",
              "components": [
                {
                  "type": "template-form",
                  "name": "form0",
                  "components": [
                    {
                      "type": "row",
                      "style": {
                        "marginBottom": "1rem"
                      },
                      "components": [
                        {
                          "type": "col",
                          "class": "col-md-3",
                          "components": [
                            {
                              "type": "label",
                              "text": "User Id",
                              "component": "USER_ID",
                              "name": "USER_IDLabel",
                              "style": {
                                "width": "100%"
                              }
                            }
                          ]
                        },
                        {
                          "type": "col",
                          "class": "col-md-9",
                          "components": [
                            {
                              "valueType": "string",
                              "maxLength": 20,
                              "type": "textbox",
                              "name": "USER_ID",
                              "style": {
                                "display": "block",
                                "width": "100%"
                              },
                              "value": "${usermst.USER_ID}"
                            },
                            {
                              "type": "required-validator",
                              "name": "USER_IDRequiredValidator",
                              "component": "USER_ID",
                              "text": "USER_ID is required",
                              "style": {
                                "position": "absolute"
                              }
                            }
                          ]
                        }
                      ]
                    },
                    {
                      "type": "row",
                      "style": {
                        "marginBottom": "1rem"
                      },
                      "components": [
                        {
                          "type": "col",
                          "class": "col-md-3",
                          "components": [
                            {
                              "type": "label",
                              "text": "Dept Name",
                              "component": "DEPT_NAME",
                              "name": "DEPT_NAMELabel",
                              "style": {
                                "width": "100%"
                              }
                            }
                          ]
                        },
                        {
                          "type": "col",
                          "class": "col-md-9",
                          "components": [
                            {
                              "valueType": "string",
                              "maxLength": 50,
                              "type": "textbox",
                              "name": "DEPT_NAME",
                              "style": {
                                "width": "100%"
                              },
                              "value": "${usermst.DEPT_NAME}"
                            }
                          ]
                        }
                      ]
                    },
                    {
                      "type": "row",
                      "style": {
                        "marginBottom": "1rem"
                      },
                      "components": [
                        {
                          "type": "col",
                          "class": "col-md-3",
                          "components": [
                            {
                              "type": "label",
                              "text": "User Name",
                              "component": "USER_NAME",
                              "name": "USER_NAMELabel",
                              "style": {
                                "width": "100%"
                              }
                            }
                          ]
                        },
                        {
                          "type": "col",
                          "class": "col-md-9",
                          "components": [
                            {
                              "valueType": "string",
                              "maxLength": 50,
                              "type": "textbox",
                              "name": "USER_NAME",
                              "style": {
                                "display": "block",
                                "width": "100%"
                              },
                              "value": "${usermst.USER_NAME}"
                            },
                            {
                              "type": "required-validator",
                              "name": "USER_NAMERequiredValidator",
                              "component": "USER_NAME",
                              "text": "USER_NAME is required",
                              "style": {
                                "position": "absolute"
                              }
                            }
                          ]
                        }
                      ]
                    },
                    {
                      "type": "row",
                      "style": {
                        "marginBottom": "1rem"
                      },
                      "components": [
                        {
                          "type": "col",
                          "class": "col-md-3",
                          "components": [
                            {
                              "type": "label",
                              "text": "User Pswd",
                              "component": "USER_PSWD",
                              "name": "USER_PSWDLabel",
                              "style": {
                                "width": "100%"
                              }
                            }
                          ]
                        },
                        {
                          "type": "col",
                          "class": "col-md-9",
                          "components": [
                            {
                              "valueType": "string",
                              "maxLength": 50,
                              "type": "textbox",
                              "name": "USER_PSWD",
                              "style": {
                                "display": "block",
                                "width": "100%"
                              },
                              "value": "${usermst.USER_PSWD}"
                            },
                            {
                              "type": "required-validator",
                              "name": "USER_PSWDRequiredValidator",
                              "component": "USER_PSWD",
                              "text": "USER_PSWD is required",
                              "style": {
                                "position": "absolute"
                              }
                            }
                          ]
                        }
                      ]
                    },
                    {
                      "type": "row",
                      "style": {
                        "marginBottom": "1rem"
                      },
                      "components": [
                        {
                          "type": "col",
                          "class": "col-md-3",
                          "components": [
                            {
                              "type": "label",
                              "text": "Telphone",
                              "component": "TELPHONE",
                              "name": "TELPHONELabel",
                              "style": {
                                "width": "100%"
                              }
                            }
                          ]
                        },
                        {
                          "type": "col",
                          "class": "col-md-9",
                          "components": [
                            {
                              "valueType": "string",
                              "maxLength": 50,
                              "type": "textbox",
                              "name": "TELPHONE",
                              "style": {
                                "width": "100%"
                              },
                              "value": "${usermst.TELPHONE}"
                            }
                          ]
                        }
                      ]
                    },
                    {
                      "type": "row",
                      "style": {
                        "marginBottom": "1rem"
                      },
                      "components": [
                        {
                          "type": "col",
                          "class": "col-md-3",
                          "components": [
                            {
                              "type": "label",
                              "text": "Mobile",
                              "component": "MOBILE",
                              "name": "MOBILELabel",
                              "style": {
                                "width": "100%"
                              }
                            }
                          ]
                        },
                        {
                          "type": "col",
                          "class": "col-md-9",
                          "components": [
                            {
                              "valueType": "string",
                              "maxLength": 50,
                              "type": "textbox",
                              "name": "MOBILE",
                              "style": {
                                "width": "100%"
                              },
                              "value": "${usermst.MOBILE}"
                            }
                          ]
                        }
                      ]
                    },
                    {
                      "type": "row",
                      "style": {
                        "marginBottom": "1rem"
                      },
                      "components": [
                        {
                          "type": "col",
                          "class": "col-md-3",
                          "components": [
                            {
                              "type": "label",
                              "text": "Email",
                              "component": "EMAIL",
                              "name": "EMAILLabel",
                              "style": {
                                "width": "100%"
                              }
                            }
                          ]
                        },
                        {
                          "type": "col",
                          "class": "col-md-9",
                          "components": [
                            {
                              "valueType": "string",
                              "maxLength": 50,
                              "type": "textbox",
                              "name": "EMAIL",
                              "style": {
                                "width": "100%"
                              },
                              "value": "${usermst.EMAIL}"
                            }
                          ]
                        }
                      ]
                    },
                    {
                      "type": "row",
                      "style": {
                        "marginBottom": "1rem"
                      },
                      "components": [
                        {
                          "type": "col",
                          "class": "col-md-3",
                          "components": [
                            {
                              "type": "label",
                              "text": "Language",
                              "component": "LANGUAGE",
                              "name": "LANGUAGELabel",
                              "style": {
                                "width": "100%"
                              }
                            }
                          ]
                        },
                        {
                          "type": "col",
                          "class": "col-md-9",
                          "components": [
                            {
                              "valueType": "string",
                              "maxLength": 2,
                              "type": "textbox",
                              "name": "LANGUAGE",
                              "style": {
                                "width": "100%"
                              },
                              "value": "${usermst.LANGUAGE}"
                            }
                          ]
                        }
                      ]
                    },
                    {
                      "type": "row",
                      "style": {
                        "marginBottom": "1rem"
                      },
                      "components": [
                        {
                          "type": "col",
                          "class": "col-md-3",
                          "components": [
                            {
                              "type": "label",
                              "text": "Enable",
                              "component": "ENABLE",
                              "name": "ENABLELabel",
                              "style": {
                                "width": "100%"
                              }
                            }
                          ]
                        },
                        {
                          "type": "col",
                          "class": "col-md-9",
                          "components": [
                            {
                              "valueType": "string",
                              "maxLength": 1,
                              "type": "textbox",
                              "name": "ENABLE",
                              "style": {
                                "width": "100%"
                              },
                              "value": "${usermst.ENABLE}"
                            }
                          ]
                        }
                      ]
                    },
                    {
                      "type": "row",
                      "style": {
                        "marginBottom": "1rem"
                      },
                      "components": [
                        {
                          "type": "col",
                          "class": "col-md-3",
                          "components": [
                            {
                              "type": "label",
                              "text": "Remark",
                              "component": "REMARK",
                              "name": "REMARKLabel",
                              "style": {
                                "width": "100%"
                              }
                            }
                          ]
                        },
                        {
                          "type": "col",
                          "class": "col-md-9",
                          "components": [
                            {
                              "valueType": "string",
                              "type": "textbox",
                              "name": "REMARK",
                              "style": {
                                "width": "100%"
                              },
                              "value": "${usermst.REMARK}"
                            }
                          ]
                        }
                      ]
                    },
                    {
                      "type": "row",
                      "style": {
                        "marginBottom": "1rem"
                      },
                      "components": [
                        {
                          "type": "col",
                          "class": "col-md-3",
                          "components": [
                            {
                              "type": "label",
                              "text": "Trn User",
                              "component": "TRN_USER",
                              "name": "TRN_USERLabel",
                              "style": {
                                "width": "100%"
                              }
                            }
                          ]
                        },
                        {
                          "type": "col",
                          "class": "col-md-9",
                          "components": [
                            {
                              "valueType": "string",
                              "maxLength": 50,
                              "type": "textbox",
                              "name": "TRN_USER",
                              "style": {
                                "display": "block",
                                "width": "100%"
                              },
                              "value": "${usermst.TRN_USER}"
                            },
                            {
                              "type": "required-validator",
                              "name": "TRN_USERRequiredValidator",
                              "component": "TRN_USER",
                              "text": "TRN_USER is required",
                              "style": {
                                "position": "absolute"
                              }
                            }
                          ]
                        }
                      ]
                    },
                    {
                      "type": "row",
                      "style": {
                        "marginBottom": "1rem"
                      },
                      "components": [
                        {
                          "type": "col",
                          "class": "col-md-3",
                          "components": [
                            {
                              "type": "label",
                              "text": "Trn Date",
                              "component": "TRN_DATE",
                              "name": "TRN_DATELabel",
                              "style": {
                                "width": "100%"
                              }
                            }
                          ]
                        },
                        {
                          "type": "col",
                          "class": "col-md-9",
                          "components": [
                            {
                              "valueType": "string",
                              "maxLength": 20,
                              "type": "textbox",
                              "name": "TRN_DATE",
                              "style": {
                                "width": "100%"
                              },
                              "value": "${usermst.TRN_DATE}"
                            }
                          ]
                        }
                      ]
                    },
                    {
                      "type": "row",
                      "style": {
                        "marginBottom": "1rem"
                      },
                      "components": [
                        {
                          "type": "col",
                          "class": "col-md-3",
                          "components": [
                            {
                              "type": "label",
                              "text": "Crt User",
                              "component": "CRT_USER",
                              "name": "CRT_USERLabel",
                              "style": {
                                "width": "100%"
                              }
                            }
                          ]
                        },
                        {
                          "type": "col",
                          "class": "col-md-9",
                          "components": [
                            {
                              "valueType": "string",
                              "maxLength": 50,
                              "type": "textbox",
                              "name": "CRT_USER",
                              "style": {
                                "display": "block",
                                "width": "100%"
                              },
                              "value": "${usermst.CRT_USER}"
                            },
                            {
                              "type": "required-validator",
                              "name": "CRT_USERRequiredValidator",
                              "component": "CRT_USER",
                              "text": "CRT_USER is required",
                              "style": {
                                "position": "absolute"
                              }
                            }
                          ]
                        }
                      ]
                    },
                    {
                      "type": "row",
                      "style": {
                        "marginBottom": "1rem"
                      },
                      "components": [
                        {
                          "type": "col",
                          "class": "col-md-3",
                          "components": [
                            {
                              "type": "label",
                              "text": "Crt Date",
                              "component": "CRT_DATE",
                              "name": "CRT_DATELabel",
                              "style": {
                                "width": "100%"
                              }
                            }
                          ]
                        },
                        {
                          "type": "col",
                          "class": "col-md-9",
                          "components": [
                            {
                              "valueType": "string",
                              "maxLength": 20,
                              "type": "textbox",
                              "name": "CRT_DATE",
                              "style": {
                                "width": "100%"
                              },
                              "value": "${usermst.CRT_DATE}"
                            }
                          ]
                        }
                      ]
                    },
                    {
                      "type": "row",
                      "style": {
                        "marginBottom": "1rem"
                      },
                      "components": [
                        {
                          "type": "col",
                          "class": "col-md-3",
                          "components": [
                            {
                              "type": "label",
                              "text": "Pswd Date",
                              "component": "PSWD_DATE",
                              "name": "PSWD_DATELabel",
                              "style": {
                                "width": "100%"
                              }
                            }
                          ]
                        },
                        {
                          "type": "col",
                          "class": "col-md-9",
                          "components": [
                            {
                              "valueType": "string",
                              "maxLength": 20,
                              "type": "textbox",
                              "name": "PSWD_DATE",
                              "style": {
                                "width": "100%"
                              },
                              "value": "${usermst.PSWD_DATE}"
                            }
                          ]
                        }
                      ]
                    },
                    {
                      "type": "row",
                      "style": {
                        "marginBottom": "1rem"
                      },
                      "components": [
                        {
                          "type": "col",
                          "class": "col-md-3",
                          "components": [
                            {
                              "type": "label",
                              "text": "Last Date",
                              "component": "LAST_DATE",
                              "name": "LAST_DATELabel",
                              "style": {
                                "width": "100%"
                              }
                            }
                          ]
                        },
                        {
                          "type": "col",
                          "class": "col-md-9",
                          "components": [
                            {
                              "valueType": "string",
                              "maxLength": 20,
                              "type": "textbox",
                              "name": "LAST_DATE",
                              "style": {
                                "width": "100%"
                              },
                              "value": "${usermst.LAST_DATE}"
                            }
                          ]
                        }
                      ]
                    },
                    {
                      "type": "row",
                      "components": [
                        {
                          "type": "col",
                          "class": "col offset-sm-3",
                          "components": [
                            {
                              "type": "button",
                              "buttonType": "submit",
                              "icon": "save",
                              "text": "Save",
                              "buttonStyle": "primary"
                            },
                            {
                              "type": "button",
                              "buttonStyle": "light",
                              "style": {
                                "marginLeft": "1rem"
                              },
                              "text": "Cancel",
                              "events": {
                                "click": [
                                  {
                                    "type": "close-popup"
                                  }
                                ]
                              }
                            }
                          ]
                        }
                      ]
                    }
                  ],
                  "events": {
                    "submit": [
                      {
                        "error": [
                          {
                            "detail": "Unable to update UserMst",
                            "severity": "error",
                            "summary": "Error",
                            "type": "notify"
                          }
                        ],
                        "name": "MARK10_SQLEXPRESS04.updateUserMst",
                        "parameters": [
                          {
                            "name": "USER_ID",
                            "value": "${parameters.USER_ID}"
                          },
                          {
                            "name": "UserMst",
                            "value": "${usermst}"
                          }
                        ],
                        "then": [
                          {
                            "type": "close-popup",
                            "result": "${usermst}",
                            "condition": ""
                          }
                        ],
                        "type": "invoke"
                      }
                    ]
                  },
                  "itemType": "RadzenDh5.Models.Mark10Sqlexpress04.UserMst",
                  "data": "${usermst}",
                  "visible": "${usermst != null}"
                }
              ]
            }
          ]
        }
      ]
    }
  ],
  "events": {
    "load": [
      {
        "name": "MARK10_SQLEXPRESS04.getUserMstByUSER_ID",
        "parameters": [
          {
            "name": "USER_ID",
            "value": "${parameters.USER_ID}"
          }
        ],
        "then": [
          {
            "name": "usermst",
            "type": "set",
            "value": "${result}",
            "valueType": "RadzenDh5.Models.Mark10Sqlexpress04.UserMst"
          }
        ],
        "error": [],
        "type": "invoke"
      }
    ]
  },
  "name": "Edit User Mst",
  "access": [
    "Authenticated"
  ],
  "layout": "Main"
}